archive_file_urls/__init__.py
archive_file_urls/__main__.py
archive_file_urls/cli.py
archive_file_urls-1.1.2.dist-info/entry_points.txt
archive_file_urls-1.1.2.dist-info/WHEEL
archive_file_urls-1.1.2.dist-info/METADATA
archive_file_urls-1.1.2.dist-info/RECORD
