Metadata-Version: 2.1
Name: archive-file-urls
Version: 1.1.2
Summary: Submit URLs listed inside a file to website archival services
Home-page: https://github.com/Quoorex/archive-file-urls
License: MIT
Keywords: Archiving
Author: Quoorex
Author-email: 46283604+Quoorex@users.noreply.github.com
Requires-Python: >=3.9,<4.0
Classifier: License :: OSI Approved :: MIT License
Classifier: Programming Language :: Python :: 3
Classifier: Programming Language :: Python :: 3.9
Requires-Dist: archivenow (>=2020.7.18,<2021.0.0)
Project-URL: Repository, https://github.com/Quoorex/archive-file-urls
